sql_infer/bin/__init__.py
sql_infer/bin/sql-infer-linux
sql_infer/bin/sql-infer-macos
sql_infer/bin/sql-infer-win.exe
sql_infer/__init__.py
sql_infer/main.py
sql_infer-0.15.0.dist-info/METADATA
sql_infer-0.15.0.dist-info/WHEEL
sql_infer-0.15.0.dist-info/entry_points.txt
sql_infer-0.15.0.dist-info/RECORD
