Metadata-Version: 2.4
Name: sql-infer
Version: 0.15.0
Summary: SQL Infer Python Wrapper
Author: jnlt3
Author-email: dsekercioglu2003@gmail.com
Requires-Python: >=3.12,<4.0
Classifier: Programming Language :: Python :: 3
Classifier: Programming Language :: Python :: 3.12
Classifier: Programming Language :: Python :: 3.13
Classifier: Programming Language :: Python :: 3.14
